{
  "project_info": {
    "project_number": "760964256580",
    "project_id": "musedbyme-220ef",
    "storage_bucket": "musedbyme-220ef.appspot.com"
  },
  "client": [
    {
      "client_info": {
        "mobilesdk_app_id": "1:760964256580:android:feedfba9a160ec3ec1bd11",
        "android_client_info": {
          "package_name": "com.example.google_auth"
        }
      },
      "oauth_client": [
        {
          "client_id": "760964256580-jegtu6q0d3u451cc42rfnjq8bi4om0g3.apps.googleusercontent.com",
          "client_type": 3
        }
      ],
      "api_key": [
        {
          "current_key": "AIzaSyAL-T9lTekwFXsDoVkOaUXbaJcmv9_oJ70"
        }
      ],
      "services": {
        "appinvite_service": {
          "other_platform_oauth_client": [
            {
              "client_id": "760964256580-jegtu6q0d3u451cc42rfnjq8bi4om0g3.apps.googleusercontent.com",
              "client_type": 3
            },
            {
              "client_id": "760964256580-lfpvs22phagevmg6kithb20msl1taio4.apps.googleusercontent.com",
              "client_type": 2,
              "ios_info": {
                "bundle_id": "com.example.musedme"
              }
            }
          ]
        }
      }
    },
    {
      "client_info": {
        "mobilesdk_app_id": "1:760964256580:android:8f0757078787a0a4c1bd11",
        "android_client_info": {
          "package_name": "com.gesolucions.musedme"
        }
      },
      "oauth_client": [
        {
          "client_id": "760964256580-urobjj9phmbff9sp8d1gilq4jgpdn3fa.apps.googleusercontent.com",
          "client_type": 1,
          "android_info": {
            "package_name": "com.gesolucions.musedme",
            "certificate_hash": "cb175749757e1826adf87b8bd2577c400859d8aa"
          }
        },
        {
          "client_id": "760964256580-jegtu6q0d3u451cc42rfnjq8bi4om0g3.apps.googleusercontent.com",
          "client_type": 3
        }
      ],
      "api_key": [
        {
          "current_key": "AIzaSyAL-T9lTekwFXsDoVkOaUXbaJcmv9_oJ70"
        }
      ],
      "services": {
        "appinvite_service": {
          "other_platform_oauth_client": [
            {
              "client_id": "760964256580-jegtu6q0d3u451cc42rfnjq8bi4om0g3.apps.googleusercontent.com",
              "client_type": 3
            },
            {
              "client_id": "760964256580-lfpvs22phagevmg6kithb20msl1taio4.apps.googleusercontent.com",
              "client_type": 2,
              "ios_info": {
                "bundle_id": "com.example.musedme"
              }
            }
          ]
        }
      }
    }
  ],
  "configuration_version": "1"
}